generate_gizmosql_token/__init__.py
generate_gizmosql_token/main.py
generate_gizmosql_token-0.0.14.dist-info/METADATA
generate_gizmosql_token-0.0.14.dist-info/WHEEL
generate_gizmosql_token-0.0.14.dist-info/entry_points.txt
generate_gizmosql_token-0.0.14.dist-info/top_level.txt
generate_gizmosql_token-0.0.14.dist-info/RECORD
