Metadata-Version: 2.4
Name: generate-gizmosql-token
Version: 0.0.14
Summary: A package which generates a GizmoSQL token (JWT) for auth testing
Author-email: Philip Moore <philip@gizmodata.com>
Project-URL: Homepage, https://github.com/gizmodata/generate-gizmosql-token
Keywords: gizmosql,auth,token,bearer,jwt
Classifier: License :: OSI Approved :: Apache Software License
Classifier: Programming Language :: Python
Classifier: Programming Language :: Python :: 3
Requires-Python: >=3.10
Requires-Dist: click==8.2.*
Requires-Dist: pyjwt==2.10.*
Requires-Dist: cryptography==45.0.*
Requires-Dist: python-dotenv==1.1.*
Provides-Extra: dev
Requires-Dist: bumpver; extra == "dev"
Requires-Dist: pip-tools; extra == "dev"
Requires-Dist: pytest; extra == "dev"
